llamazure/azgraph/__init__.py
llamazure/azgraph/azgraph.py
llamazure/azgraph/codec.py
llamazure/azgraph/models.py
llamazure.azgraph-0.1.0.dist-info/METADATA
llamazure.azgraph-0.1.0.dist-info/WHEEL
llamazure.azgraph-0.1.0.dist-info/namespace_packages.txt
llamazure.azgraph-0.1.0.dist-info/top_level.txt
llamazure.azgraph-0.1.0.dist-info/RECORD
